getoutvideo/__init__.py
getoutvideo/ai_processor.py
getoutvideo/audio_transcriber.py
getoutvideo/config.py
getoutvideo/config_urls.py
getoutvideo/exceptions.py
getoutvideo/models.py
getoutvideo/prompts.py
getoutvideo/transcript_extractor.py
getoutvideo/utils.py
getoutvideo-1.1.1.dist-info/licenses/LICENSE
getoutvideo-1.1.1.dist-info/METADATA
getoutvideo-1.1.1.dist-info/WHEEL
getoutvideo-1.1.1.dist-info/top_level.txt
getoutvideo-1.1.1.dist-info/RECORD
