Metadata-Version: 2.4
Name: getoutvideo
Version: 1.1.1
Summary: Extract and process YouTube video transcripts with AI
Home-page: https://github.com/keboom/GetOutVideo-api
Author: GetOutVideo API
Author-email: GetOutVideo API <keboom.dev@gmail.com>
License: MIT
Project-URL: Homepage, https://github.com/keboom/GetOutVideo-api
Project-URL: Documentation, https://github.com/keboom/GetOutVideo-api#readme
Project-URL: Repository, https://github.com/keboom/GetOutVideo-api
Project-URL: Issues, https://github.com/keboom/GetOutVideo-api/issues
Keywords: youtube,transcript,ai,openai,video-processing,gpt
Classifier: Development Status :: 4 - Beta
Classifier: Intended Audience :: Developers
Classifier: License :: OSI Approved :: MIT License
Classifier: Programming Language :: Python :: 3
Classifier: Programming Language :: Python :: 3.8
Classifier: Programming Language :: Python :: 3.9
Classifier: Programming Language :: Python :: 3.10
Classifier: Programming Language :: Python :: 3.11
Classifier: Topic :: Multimedia :: Video
Classifier: Topic :: Scientific/Engineering :: Artificial Intelligence
Classifier: Topic :: Text Processing
Requires-Python: >=3.8
License-File: LICENSE
Requires-Dist: pytubefix
Requires-Dist: youtube-transcript-api
Requires-Dist: openai>=1.75.0
Requires-Dist: python-dotenv
Requires-Dist: yt-dlp
Requires-Dist: pydub
Requires-Dist: ffmpeg-python
Provides-Extra: dev
Requires-Dist: pytest>=7.0; extra == "dev"
Requires-Dist: black; extra == "dev"
Requires-Dist: flake8; extra == "dev"
Requires-Dist: mypy; extra == "dev"
Requires-Dist: twine; extra == "dev"
Requires-Dist: build; extra == "dev"
Provides-Extra: test
Requires-Dist: pytest>=7.0; extra == "test"
Requires-Dist: pytest-cov; extra == "test"
Dynamic: author
Dynamic: home-page
Dynamic: license-file
Dynamic: requires-python
